infobus/__init__.py
infobus/cli.py
infobus/client.py
infobus/exceptions.py
infobus/models.py
infobus-0.1.0.dist-info/METADATA
infobus-0.1.0.dist-info/WHEEL
infobus-0.1.0.dist-info/entry_points.txt
infobus-0.1.0.dist-info/licenses/LICENSE
infobus-0.1.0.dist-info/RECORD
