Metadata-Version: 2.4
Name: infobus
Version: 0.1.0
Summary: A Python client library and CLI tools for accessing Infobús external APIs and integrating transit data into research workflows
Project-URL: Homepage, https://github.com/simovilab/infobus-py
Project-URL: Repository, https://github.com/simovilab/infobus-py
Project-URL: Documentation, https://github.com/simovilab/infobus-py#readme
Project-URL: Bug Tracker, https://github.com/simovilab/infobus-py/issues
Author-email: Fabián Abarca <ensinergia@gmail.com>
License: Apache-2.0
License-File: LICENSE
Keywords: api-client,gtfs,public-transportation,research,transit
Classifier: Development Status :: 3 - Alpha
Classifier: Intended Audience :: Developers
Classifier: Intended Audience :: Science/Research
Classifier: License :: OSI Approved :: Apache Software License
Classifier: Operating System :: OS Independent
Classifier: Programming Language :: Python :: 3
Classifier: Programming Language :: Python :: 3.9
Classifier: Programming Language :: Python :: 3.10
Classifier: Programming Language :: Python :: 3.11
Classifier: Programming Language :: Python :: 3.12
Classifier: Topic :: Scientific/Engineering
Classifier: Topic :: Software Development :: Libraries :: Python Modules
Requires-Python: >=3.9
Requires-Dist: click>=8.0.0
Requires-Dist: pydantic>=2.0.0
Requires-Dist: python-dateutil>=2.8.0
Requires-Dist: requests>=2.31.0
Provides-Extra: dev
Requires-Dist: black>=23.0.0; extra == 'dev'
Requires-Dist: isort>=5.12.0; extra == 'dev'
Requires-Dist: mypy>=1.0.0; extra == 'dev'
Requires-Dist: pre-commit>=3.0.0; extra == 'dev'
Requires-Dist: pytest-cov>=4.0.0; extra == 'dev'
Requires-Dist: pytest>=7.0.0; extra == 'dev'
Provides-Extra: docs
Requires-Dist: mkdocs-click>=0.8.0; extra == 'docs'
Requires-Dist: mkdocs-material>=9.0.0; extra == 'docs'
